format_sql-0.12.0.dist-info/metadata.json
format_sql-0.12.0.dist-info/RECORD
format_sql-0.12.0.dist-info/DESCRIPTION.rst
format_sql-0.12.0.dist-info/pbr.json
format_sql-0.12.0.dist-info/entry_points.txt
format_sql-0.12.0.dist-info/METADATA
format_sql-0.12.0.dist-info/top_level.txt
format_sql-0.12.0.dist-info/WHEEL
format_sql/styler.py
format_sql/__init__.py
format_sql/tokenizer.py
format_sql/shortcuts.py
format_sql/main.py
format_sql/parser.py
format_sql/util.py
